mqtt_mcp/__init__.py
mqtt_mcp/cli.py
mqtt_mcp/mqtt_client.py
mqtt_mcp/server.py
mqtt_mcp/settings.py
mqtt_mcp-0.2.8.dist-info/METADATA
mqtt_mcp-0.2.8.dist-info/WHEEL
mqtt_mcp-0.2.8.dist-info/entry_points.txt
mqtt_mcp-0.2.8.dist-info/licenses/LICENSE
mqtt_mcp-0.2.8.dist-info/RECORD
