Metadata-Version: 2.4
Name: mqtt-mcp
Version: 0.2.8
Summary: A Model Context Protocol (MCP) server for MQTT
License-File: LICENSE
Requires-Python: >=3.13
Requires-Dist: fastmcp>=2.11.0
Requires-Dist: paho-mqtt>=2.1.0
Requires-Dist: pydantic-settings>=2.10.0
Requires-Dist: typer>=0.16.0
